Metadata-Version: 2.1
Name: distributions-prob-tiamiyu
Version: 1.0
Summary: Gaussian distributions
License: UNKNOWN
Platform: UNKNOWN
